snowlock/__init__.py
snowlock/_version.py
snowlock/lock.py
snowlock/utils.py
snowlock-1.0.0.dist-info/LICENSE
snowlock-1.0.0.dist-info/METADATA
snowlock-1.0.0.dist-info/WHEEL
snowlock-1.0.0.dist-info/top_level.txt
snowlock-1.0.0.dist-info/RECORD
